greenhack/00-ipython-startup.py
greenhack/__init__.py
greenhack/_loop.py
greenhack/as_async.py
greenhack/context_managers.py
greenhack/context_vars.py
greenhack/exempt.py
greenhack/ipy.py
greenhack/iterators.py
greenhack/start_loop.py
greenhack/utils.py
sieve_toolkit-0.1.12.dist-info/METADATA
sieve_toolkit-0.1.12.dist-info/WHEEL
sieve_toolkit-0.1.12.dist-info/top_level.txt
sieve_toolkit-0.1.12.dist-info/RECORD
