Metadata-Version: 2.1
Name: sieve-toolkit
Version: 0.1.12
Summary: greenhack
Author: Vitalii Abetkin
Author-email: abvit89s@gmail.ru
License: MIT
Requires-Dist: greenlet
